plone.folder-4.0.1-py3.12-nspkg.pth
plone/folder/__init__.py
plone/folder/configure.zcml
plone/folder/default.py
plone/folder/interfaces.py
plone/folder/nogopip.py
plone/folder/ordered.py
plone/folder/partial.py
plone/folder/testing.py
plone/folder/unordered.py
plone/folder/dtml/addGopipIndex.dtml
plone/folder/tests/__init__.py
plone/folder/tests/benchmarks.py
plone/folder/tests/test_dict_interface.py
plone/folder/tests/test_integration.py
plone/folder/tests/test_ordering_adapters.py
plone/folder/tests/test_ordersupport.py
plone/folder/tests/test_partialordering.py
plone/folder/tests/test_unorderedordering.py
plone/folder/tests/test_webdav.py
plone/folder/tests/utils.py
plone.folder-4.0.1.dist-info/METADATA
plone.folder-4.0.1.dist-info/WHEEL
plone.folder-4.0.1.dist-info/namespace_packages.txt
plone.folder-4.0.1.dist-info/top_level.txt
plone.folder-4.0.1.dist-info/RECORD
