Metadata-Version: 2.1
Name: plone.folder
Version: 4.0.1
Summary: BTree-based folder implementation with order support
Home-page: https://pypi.org/project/plone.folder
Author: Plone Foundation
Author-email: plone-developers@lists.sourceforge.net
License: GPL version 2
Keywords: folder btree order
Platform: Any
Classifier: Development Status :: 5 - Production/Stable
Classifier: Environment :: Web Environment
Classifier: Framework :: Plone
Classifier: Framework :: Plone :: 6.0
Classifier: Framework :: Plone :: Core
Classifier: Framework :: Zope2
Classifier: Framework :: Zope :: 4
Classifier: Intended Audience :: Developers
Classifier: Intended Audience :: System Administrators
Classifier: Intended Audience :: Other Audience
Classifier: License :: OSI Approved :: GNU General Public License v2 (GPLv2)
Classifier: Operating System :: OS Independent
Classifier: Programming Language :: Python
Classifier: Programming Language :: Python :: 3.8
Classifier: Programming Language :: Python :: 3.9
Classifier: Programming Language :: Python :: 3.10
Classifier: Programming Language :: Python :: 3.11
Requires-Python: >=3.8
Requires-Dist: setuptools
Requires-Dist: Products.CMFCore
Requires-Dist: Products.ZCatalog
Requires-Dist: Zope
Provides-Extra: test
Requires-Dist: plone.app.testing ; extra == 'test'
Requires-Dist: profilehooks ; extra == 'test'
